<?xml version="1.0" encoding="UTF-8" standalone="no"?>
<config>
	<StartPort>40000</StartPort>
	<registerURI>coap://10.0.0.7:3131/register</registerURI>
	<hostname>10.0.0.11</hostname>
	<DeviationAmperageConsumerPersent>60</DeviationAmperageConsumerPersent>	
	<AverageAmperageConsumer>6.0</AverageAmperageConsumer>	
	<AverageResistanceOnWire>7.5</AverageResistanceOnWire>
	<AverageVoltageOrigin>220.0</AverageVoltageOrigin>	
	<DeviationResistanceOnWirePersent>33</DeviationResistanceOnWirePersent>
	<NumberOfMiddleMeter>2</NumberOfMiddleMeter>
	<NumberOfConsumerMeter>7</NumberOfConsumerMeter>
	<StartDelay>60000</StartDelay>
	<WorkDelay>30000</WorkDelay>
	<DeviationVoltageOriginPersent>5</DeviationVoltageOriginPersent>
</config>